screenshotgenerator/__init__.py
screenshotgenerator/click_enum_type.py
screenshotgenerator/common.py
screenshotgenerator/defaults.py
screenshotgenerator/generate.py
screenshotgenerator/portrait_preference.py
screenshotgenerator/screenshot.py
screenshotgenerator/screenshotgenerator.py
screenshotgenerator/screenshotselector.py
screenshotgenerator/select.py
screenshotgenerator-0.4.0.dist-info/LICENSE
screenshotgenerator-0.4.0.dist-info/METADATA
screenshotgenerator-0.4.0.dist-info/WHEEL
screenshotgenerator-0.4.0.dist-info/entry_points.txt
screenshotgenerator-0.4.0.dist-info/top_level.txt
screenshotgenerator-0.4.0.dist-info/RECORD
