Metadata-Version: 2.1
Name: screenshotgenerator
Version: 0.4.0
Summary: A library for automatically generating and selecting video screenshots.
Author: jonbenta
Project-URL: Homepage, https://github.com/jonbenta/ScreenshotGenerator
Project-URL: Bug Tracker, https://github.com/jonbenta/ScreenshotGenerator/issues
Classifier: Development Status :: 4 - Beta
Classifier: License :: OSI Approved :: MIT License
Classifier: Operating System :: OS Independent
Classifier: Programming Language :: Python :: 3
Classifier: Topic :: Multimedia :: Video
Classifier: Topic :: Scientific/Engineering :: Image Recognition
Requires-Python: <3.11,>=3.8
License-File: LICENSE
Requires-Dist: autogluon
Requires-Dist: click
Requires-Dist: gdown
Requires-Dist: platformdirs
Requires-Dist: pymediainfo
